setup.py
peak_analysis/GaussianPeakAnalysis.py
peak_analysis/PeakAnalysis.py
peak_analysis/__init__.py
peak_analysis/helper.py
peak_analysis_modified.egg-info/PKG-INFO
peak_analysis_modified.egg-info/SOURCES.txt
peak_analysis_modified.egg-info/dependency_links.txt
peak_analysis_modified.egg-info/not-zip-safe
peak_analysis_modified.egg-info/top_level.txt