Metadata-Version: 1.0
Name: peak-analysis-modified
Version: 0.2
Summary: Gaussian Peak Analysis
Home-page: UNKNOWN
Author: Qian Liu
Author-email: UNKNOWN
License: UNKNOWN
Platform: UNKNOWN
